{
    "shapes": [
        "Circle",
        "Oval",
        "Rectangle",
        "Square",
        "Triangle"
    ],
    "physical nature": [
        "Boy",
        "Bird",
        "Cat",
        "Dog",
        "Girl",
        "Man",
        "Plant",
        "Woman"
    ],
    "distinguishing characteristic": [
        "Acrobat",
        "Alien",
        "Astronaut",
        "Astronomer/Scientist",
        "Bookworm",
        "Chef",
        "Cowboy/cowgirl",
        "Detective",
        "Kung Fu Master",
        "Magician",
        "Pirate",
        "Sky Diver",
        "Snowboarder/Skater",
        "Teacher",
        "Train Operator",
        "Witch/Warlock"
    ],
    "items": [
        "Bed Sheets",
        "Books",
        "Bows",
        "Candle",
        "Candy",
        "Chair",
        "Childrens Toys",
        "Clouds",
        "Coat",
        "Collar",
        "Dog Toys",
        "Door Knob",
        "Dress",
        "Eggs",
        "Fashion",
        "Flowers",
        "Food",
        "Food",
        "Fruit",
        "Game pieces",
        "Glasses",
        "Gloves",
        "Items you would find in a pocket",
        "Kitchen Utensils",
        "Lace",
        "Lamps",
        "Leash",
        "Necklace",
        "Pair of shoes",
        "Pants",
        "Pillow",
        "Playing Cards",
        "Scarves",
        "Sea Shells",
        "Shirt",
        "Shoes",
        "Skirt",
        "Socks",
        "Sports Items",
        "Swim suite",
        "Trees",
        "Vegitables",
        "Watches",
        "Weapons"
    ],
    "season": [
        "Autumn",
        "Spring",
        "Summer",
        "Winter"
    ],
    "time": [
        "Day",
        "Night"
    ],
    "inside": [
        "Bar",
        "Bathroom",
        "Bedroom",
        "Kitchen",
        "Party",
        "Spa",
        "Space Ship",
        "Space Shuttle"
    ],
    "outside": [
        "Desert",
        "Forest",
        "Grassland",
        "Mountains",
        "Ocean",
        "Plains",
        "Polar Ice",
        "Savanna",
        "Tropical Rain Forest",
        "Tundra",
        "Wetland"
    ],
    "exercise": [
        "Color",
        "Composition Techniques",
        "Contour",
        "Negative Space",
        "Perspective 3D Rotation",
        "Shading Techniques"
    ],
    "study": [
        "Cat Anatomy",
        "Clothing",
        "Dog Anatomy",
        "Fabrics",
        "Fashion",
        "Glass",
        "Human Anatomy",
        "Human Figure",
        "Still Life"
    ],
    "anatomy": [
        "Arm",
        "Back",
        "Ears",
        "Eyes",
        "Face",
        "Feet",
        "Hair",
        "Hands",
        "Leg",
        "Mouth",
        "Neck",
        "Nose",
        "Pecks",
        "Pelvis",
        "Shoulders",
        "Stomach",
        "torso"
    ],
    "emotion": [
        "Crying",
        "Fear",
        "Hope",
        "Joy",
        "Laughing"
    ]
}